pybulletX/__init__.py
pybulletX/_wrapper.py
pybulletX/body.py
pybulletX/client.py
pybulletX/contact_point.py
pybulletX/dynamics_info.py
pybulletX/helper.py
pybulletX/joint_info.py
pybulletX/joint_state.py
pybulletX/joint_type.py
pybulletX/link_state.py
pybulletX/mapping_mixin.py
pybulletX/robot.py
pybulletX/robot_interface.py
pybulletX/robot_interface_mixin.py
pybulletX/__pycache__/__init__.cpython-37.pyc
pybulletX/__pycache__/_wrapper.cpython-37.pyc
pybulletX/__pycache__/body.cpython-37.pyc
pybulletX/__pycache__/client.cpython-37.pyc
pybulletX/__pycache__/contact_point.cpython-37.pyc
pybulletX/__pycache__/dynamics_info.cpython-37.pyc
pybulletX/__pycache__/helper.cpython-37.pyc
pybulletX/__pycache__/joint_info.cpython-37.pyc
pybulletX/__pycache__/joint_state.cpython-37.pyc
pybulletX/__pycache__/joint_type.cpython-37.pyc
pybulletX/__pycache__/link_state.cpython-37.pyc
pybulletX/__pycache__/mapping_mixin.cpython-37.pyc
pybulletX/__pycache__/robot.cpython-37.pyc
pybulletX/__pycache__/robot_interface.cpython-37.pyc
pybulletX/__pycache__/robot_interface_mixin.cpython-37.pyc
pybulletX/gui/__init__.py
pybulletX/gui/control_panel.py
pybulletX/gui/__pycache__/__init__.cpython-37.pyc
pybulletX/gui/__pycache__/control_panel.cpython-37.pyc
pybulletX/utils/__init__.py
pybulletX/utils/loop_thread.py
pybulletX/utils/simulation_thread.py
pybulletX/utils/soft_real_time_clock.py
pybulletX/utils/space_dict.py
pybulletX/utils/__pycache__/__init__.cpython-37.pyc
pybulletX/utils/__pycache__/loop_thread.cpython-37.pyc
pybulletX/utils/__pycache__/simulation_thread.cpython-37.pyc
pybulletX/utils/__pycache__/soft_real_time_clock.cpython-37.pyc
pybulletX/utils/__pycache__/space_dict.cpython-37.pyc
pybulletX-0.4.1.dist-info/LICENSE
pybulletX-0.4.1.dist-info/METADATA
pybulletX-0.4.1.dist-info/WHEEL
pybulletX-0.4.1.dist-info/top_level.txt
pybulletX-0.4.1.dist-info/RECORD
