Metadata-Version: 2.1
Name: pybulletX
Version: 0.4.1
Summary: A Pythonic wrapper for pybullet
Home-page: https://github.com/facebookresearch/pybulletX
Author: Po-Wei Chou
Author-email: poweic@fb.com
License: UNKNOWN
Platform: UNKNOWN
Requires-Dist: pybullet (>=2.8.1)
Requires-Dist: numpy (>=1.18.5)
Requires-Dist: attrdict (>=2.0.1)
Requires-Dist: gym (>=0.17.2)
